qfx.py
qfx_scraper-1.0.4.dist-info/DESCRIPTION.rst
qfx_scraper-1.0.4.dist-info/METADATA
qfx_scraper-1.0.4.dist-info/RECORD
qfx_scraper-1.0.4.dist-info/WHEEL
qfx_scraper-1.0.4.dist-info/metadata.json
qfx_scraper-1.0.4.dist-info/top_level.txt
