Metadata-Version: 2.0
Name: qfx-scraper
Version: 1.0.4
Summary: A scraper for qfxcinemas.com written using requests-html package.
Home-page: https://github.com/poudel/qfx-scraper
Author: keshaB Paudel
Author-email: self@keshab.net
License: MIT
Platform: UNKNOWN
Classifier: License :: OSI Approved :: MIT License
Classifier: Programming Language :: Python
Classifier: Programming Language :: Python :: 3
Classifier: Programming Language :: Python :: 3.6
Classifier: Programming Language :: Python :: Implementation :: CPython
Classifier: Programming Language :: Python :: Implementation :: PyPy
Requires-Python: >=3.6.0
Requires-Dist: requests-html
